AUTHORS
ChangeLog
Pipfile
Pipfile.lock
README.md
README.rst
requirements.txt
scihub.py
setup.cfg
setup.py
pyslr/__init__.py
pyslr/__main__.py
pyslr.egg-info/PKG-INFO
pyslr.egg-info/SOURCES.txt
pyslr.egg-info/dependency_links.txt
pyslr.egg-info/not-zip-safe
pyslr.egg-info/pbr.json
pyslr.egg-info/requires.txt
pyslr.egg-info/top_level.txt
pyslr/common/__init__.py
pyslr/common/expression.py
pyslr/common/format.py
pyslr/find/__init__.py
pyslr/find/acm.py
pyslr/find/crossref.py
pyslr/find/find.py
pyslr/find/ieee.py
pyslr/find/scholar.py
pyslr/find/sciencedirect.py
pyslr/find/search.py
pyslr/find/springer.py
pyslr/importer/Readme.md
pyslr/importer/__init__.py
pyslr/importer/bibImporter.py