Metadata-Version: 1.1
Name: pyslr
Version: 0.0.6
Summary: Package for conducting systematic literature reviews
Home-page: https://github.com/tawalaya/pyslr
Author: Sebastian Werner
Author-email: werner@tu-berlin.de
License: Apache-2
Platform: UNKNOWN
Classifier: Development Status :: 4 - Beta
Classifier: Intended Audience :: Developers
Classifier: Intended Audience :: Science/Research
Classifier: License :: OSI Approved :: Apache Software License
Classifier: Operating System :: OS Independent
Classifier: Programming Language :: Python
Classifier: Environment :: Console
